pawz/__init__.py
pawz-0.2.1.dist-info/METADATA
pawz-0.2.1.dist-info/WHEEL
pawz-0.2.1.dist-info/licenses/LICENSE
pawz-0.2.1.dist-info/RECORD
